devyzer/__init__.py
devyzer/__main__.py
devyzer/auth.py
devyzer/cli/__init__.py
devyzer/cli/completer.py
devyzer/cli/keys.py
devyzer/cli/lexer.py
devyzer/cli/style.py
devyzer/cli/toolbar.py
devyzer/command_executor.py
devyzer/commands/__init__.py
devyzer/commands/account.py
devyzer/commands/artisan_commands.py
devyzer/commands/clone.py
devyzer/commands/git_commands.py
devyzer/commands/project_commands.py
devyzer/commands/utiles.py
devyzer/config.py
devyzer/constants.py
devyzer/main.py
devyzer/state.py
devyzer/terminal.py
devyzer/utils/__init__.py
devyzer/utils/cli.py
devyzer/utils/command.py
devyzer/utils/console.py
devyzer/utils/logger.py
devyzer-0.1.1a2.dist-info/entry_points.txt
devyzer-0.1.1a2.dist-info/LICENSE
devyzer-0.1.1a2.dist-info/WHEEL
devyzer-0.1.1a2.dist-info/METADATA
devyzer-0.1.1a2.dist-info/RECORD
